{"pageNumber":270,"juz":[15],"surahs":[18],"lines":[[{"line":1,"position":19,"textIndopak":"مِنۡ","textUthmani":"مِن","verseKey":"18:50","charType":"word"},{"line":1,"position":20,"textIndopak":"دُوۡنِىۡ","textUthmani":"دُونِى","verseKey":"18:50","charType":"word"},{"line":1,"position":21,"textIndopak":"وَهُمۡ","textUthmani":"وَهُمْ","verseKey":"18:50","charType":"word"},{"line":1,"position":22,"textIndopak":"لَـكُمۡ","textUthmani":"لَكُمْ","verseKey":"18:50","charType":"word"},{"line":1,"position":23,"textIndopak":"عَدُوٌّ ؕ","textUthmani":"عَدُوٌّۢ ۚ","verseKey":"18:50","charType":"word"},{"line":1,"position":24,"textIndopak":"بِئۡسَ","textUthmani":"بِئْسَ","verseKey":"18:50","charType":"word"},{"line":1,"position":25,"textIndopak":"لِلظّٰلِمِيۡنَ","textUthmani":"لِلظَّـٰلِمِينَ","verseKey":"18:50","charType":"word"},{"line":1,"position":26,"textIndopak":"بَدَلًا‏ ﻿﻿","textUthmani":"بَدَلًۭا","verseKey":"18:50","charType":"word"},{"line":1,"position":27,"textIndopak":"٥٠","textUthmani":"٥٠","verseKey":"18:50","charType":"end"},{"line":1,"position":1,"textIndopak":"۞ مَّاۤ","textUthmani":"۞ مَّآ","verseKey":"18:51","charType":"word"},{"line":1,"position":2,"textIndopak":"اَشۡهَدْتُّهُمۡ","textUthmani":"أَشْهَدتُّهُمْ","verseKey":"18:51","charType":"word"},{"line":1,"position":3,"textIndopak":"مُوۡسٰى","textUthmani":"مُوسَىٰ","verseKey":"18:60","charType":"word"},{"line":1,"position":4,"textIndopak":"لِفَتٰٮهُ","textUthmani":"لِفَتَىٰهُ","verseKey":"18:60","charType":"word"},{"line":1,"position":5,"textIndopak":"لَاۤ","textUthmani":"لَآ","verseKey":"18:60","charType":"word"},{"line":1,"position":6,"textIndopak":"اَبۡرَحُ","textUthmani":"أَبْرَحُ","verseKey":"18:60","charType":"word"},{"line":1,"position":7,"textIndopak":"حَتّٰۤى","textUthmani":"حَتَّىٰٓ","verseKey":"18:60","charType":"word"},{"line":1,"position":8,"textIndopak":"اَبۡلُغَ","textUthmani":"أَبْلُغَ","verseKey":"18:60","charType":"word"},{"line":1,"position":9,"textIndopak":"مَجۡمَعَ","textUthmani":"مَجْمَعَ","verseKey":"18:60","charType":"word"},{"line":1,"position":10,"textIndopak":"الۡبَحۡرَيۡنِ","textUthmani":"ٱلْبَحْرَيْنِ","verseKey":"18:60","charType":"word"},{"line":1,"position":11,"textIndopak":"اَوۡ","textUthmani":"أَوْ","verseKey":"18:60","charType":"word"},{"line":1,"position":12,"textIndopak":"اَمۡضِىَ","textUthmani":"أَمْضِىَ","verseKey":"18:60","charType":"word"},{"line":1,"position":13,"textIndopak":"حُقُبًا‏","textUthmani":"حُقُبًۭا","verseKey":"18:60","charType":"word"},{"line":1,"position":14,"textIndopak":"٦٠","textUthmani":"٦٠","verseKey":"18:60","charType":"end"}],[{"line":2,"position":3,"textIndopak":"خَلۡقَ","textUthmani":"خَلْقَ","verseKey":"18:51","charType":"word"},{"line":2,"position":4,"textIndopak":"السَّمٰوٰتِ","textUthmani":"ٱلسَّمَـٰوَٰتِ","verseKey":"18:51","charType":"word"},{"line":2,"position":5,"textIndopak":"وَالۡاَرۡضِ","textUthmani":"وَٱلْأَرْضِ","verseKey":"18:51","charType":"word"},{"line":2,"position":6,"textIndopak":"وَلَا","textUthmani":"وَلَا","verseKey":"18:51","charType":"word"},{"line":2,"position":7,"textIndopak":"خَلۡقَ","textUthmani":"خَلْقَ","verseKey":"18:51","charType":"word"},{"line":2,"position":8,"textIndopak":"اَنۡفُسِهِمۡ","textUthmani":"أَنفُسِهِمْ","verseKey":"18:51","charType":"word"},{"line":2,"position":9,"textIndopak":"وَمَا","textUthmani":"وَمَا","verseKey":"18:51","charType":"word"},{"line":2,"position":10,"textIndopak":"كُنۡتُ","textUthmani":"كُنتُ","verseKey":"18:51","charType":"word"},{"line":2,"position":11,"textIndopak":"مُتَّخِذَ","textUthmani":"مُتَّخِذَ","verseKey":"18:51","charType":"word"}],[{"line":3,"position":12,"textIndopak":"الۡمُضِلِّيۡنَ","textUthmani":"ٱلْمُضِلِّينَ","verseKey":"18:51","charType":"word"},{"line":3,"position":13,"textIndopak":"عَضُدًا‏","textUthmani":"عَضُدًۭا","verseKey":"18:51","charType":"word"},{"line":3,"position":14,"textIndopak":"٥١","textUthmani":"٥١","verseKey":"18:51","charType":"end"},{"line":3,"position":1,"textIndopak":"وَيَوۡمَ","textUthmani":"وَيَوْمَ","verseKey":"18:52","charType":"word"},{"line":3,"position":2,"textIndopak":"يَقُوۡلُ","textUthmani":"يَقُولُ","verseKey":"18:52","charType":"word"},{"line":3,"position":3,"textIndopak":"نَادُوۡا","textUthmani":"نَادُوا۟","verseKey":"18:52","charType":"word"},{"line":3,"position":4,"textIndopak":"شُرَكَآءِىَ","textUthmani":"شُرَكَآءِىَ","verseKey":"18:52","charType":"word"},{"line":3,"position":5,"textIndopak":"الَّذِيۡنَ","textUthmani":"ٱلَّذِينَ","verseKey":"18:52","charType":"word"},{"line":3,"position":6,"textIndopak":"زَعَمۡتُمۡ","textUthmani":"زَعَمْتُمْ","verseKey":"18:52","charType":"word"}],[{"line":4,"position":7,"textIndopak":"فَدَعَوۡهُمۡ","textUthmani":"فَدَعَوْهُمْ","verseKey":"18:52","charType":"word"},{"line":4,"position":8,"textIndopak":"فَلَمۡ","textUthmani":"فَلَمْ","verseKey":"18:52","charType":"word"},{"line":4,"position":9,"textIndopak":"يَسۡتَجِيۡبُوۡا","textUthmani":"يَسْتَجِيبُوا۟","verseKey":"18:52","charType":"word"},{"line":4,"position":10,"textIndopak":"لَهُمۡ","textUthmani":"لَهُمْ","verseKey":"18:52","charType":"word"},{"line":4,"position":11,"textIndopak":"وَجَعَلۡنَا","textUthmani":"وَجَعَلْنَا","verseKey":"18:52","charType":"word"},{"line":4,"position":12,"textIndopak":"بَيۡنَهُمۡ","textUthmani":"بَيْنَهُم","verseKey":"18:52","charType":"word"},{"line":4,"position":13,"textIndopak":"مَّوۡبِقًا‏","textUthmani":"مَّوْبِقًۭا","verseKey":"18:52","charType":"word"},{"line":4,"position":14,"textIndopak":"٥٢","textUthmani":"٥٢","verseKey":"18:52","charType":"end"},{"line":4,"position":1,"textIndopak":"وَرَاَ","textUthmani":"وَرَءَا","verseKey":"18:53","charType":"word"},{"line":4,"position":2,"textIndopak":"الۡمُجۡرِمُوۡنَ","textUthmani":"ٱلْمُجْرِمُونَ","verseKey":"18:53","charType":"word"}],[{"line":5,"position":3,"textIndopak":"النَّارَ","textUthmani":"ٱلنَّارَ","verseKey":"18:53","charType":"word"},{"line":5,"position":4,"textIndopak":"فَظَنُّوۡۤا","textUthmani":"فَظَنُّوٓا۟","verseKey":"18:53","charType":"word"},{"line":5,"position":5,"textIndopak":"اَنَّهُمۡ","textUthmani":"أَنَّهُم","verseKey":"18:53","charType":"word"},{"line":5,"position":6,"textIndopak":"مُّوَاقِعُوۡهَا","textUthmani":"مُّوَاقِعُوهَا","verseKey":"18:53","charType":"word"},{"line":5,"position":7,"textIndopak":"وَ لَمۡ","textUthmani":"وَلَمْ","verseKey":"18:53","charType":"word"},{"line":5,"position":8,"textIndopak":"يَجِدُوۡا","textUthmani":"يَجِدُوا۟","verseKey":"18:53","charType":"word"},{"line":5,"position":9,"textIndopak":"عَنۡهَا","textUthmani":"عَنْهَا","verseKey":"18:53","charType":"word"},{"line":5,"position":10,"textIndopak":"مَصۡرِفًا‏","textUthmani":"مَصْرِفًۭا","verseKey":"18:53","charType":"word"},{"line":5,"position":11,"textIndopak":"٥٣","textUthmani":"٥٣","verseKey":"18:53","charType":"end"},{"line":5,"position":1,"textIndopak":"وَلَقَدۡ","textUthmani":"وَلَقَدْ","verseKey":"18:54","charType":"word"}],[{"line":6,"position":2,"textIndopak":"صَرَّفۡنَا","textUthmani":"صَرَّفْنَا","verseKey":"18:54","charType":"word"},{"line":6,"position":3,"textIndopak":"فِىۡ","textUthmani":"فِى","verseKey":"18:54","charType":"word"},{"line":6,"position":4,"textIndopak":"هٰذَا","textUthmani":"هَـٰذَا","verseKey":"18:54","charType":"word"},{"line":6,"position":5,"textIndopak":"الۡقُرۡاٰنِ","textUthmani":"ٱلْقُرْءَانِ","verseKey":"18:54","charType":"word"},{"line":6,"position":6,"textIndopak":"لِلنَّاسِ","textUthmani":"لِلنَّاسِ","verseKey":"18:54","charType":"word"},{"line":6,"position":7,"textIndopak":"مِنۡ","textUthmani":"مِن","verseKey":"18:54","charType":"word"},{"line":6,"position":8,"textIndopak":"كُلِّ","textUthmani":"كُلِّ","verseKey":"18:54","charType":"word"},{"line":6,"position":9,"textIndopak":"مَثَلٍ​ ؕ","textUthmani":"مَثَلٍۢ ۚ","verseKey":"18:54","charType":"word"},{"line":6,"position":10,"textIndopak":"وَكَانَ","textUthmani":"وَكَانَ","verseKey":"18:54","charType":"word"},{"line":6,"position":11,"textIndopak":"الۡاِنۡسَانُ","textUthmani":"ٱلْإِنسَـٰنُ","verseKey":"18:54","charType":"word"},{"line":6,"position":12,"textIndopak":"اَكۡثَرَ","textUthmani":"أَكْثَرَ","verseKey":"18:54","charType":"word"}],[{"line":7,"position":13,"textIndopak":"شَىۡءٍ","textUthmani":"شَىْءٍۢ","verseKey":"18:54","charType":"word"},{"line":7,"position":14,"textIndopak":"جَدَلًا‏","textUthmani":"جَدَلًۭا","verseKey":"18:54","charType":"word"},{"line":7,"position":15,"textIndopak":"٥٤","textUthmani":"٥٤","verseKey":"18:54","charType":"end"},{"line":7,"position":1,"textIndopak":"وَمَا","textUthmani":"وَمَا","verseKey":"18:55","charType":"word"},{"line":7,"position":2,"textIndopak":"مَنَعَ","textUthmani":"مَنَعَ","verseKey":"18:55","charType":"word"},{"line":7,"position":3,"textIndopak":"النَّاسَ","textUthmani":"ٱلنَّاسَ","verseKey":"18:55","charType":"word"},{"line":7,"position":4,"textIndopak":"اَنۡ","textUthmani":"أَن","verseKey":"18:55","charType":"word"},{"line":7,"position":5,"textIndopak":"يُّؤۡمِنُوۡۤا","textUthmani":"يُؤْمِنُوٓا۟","verseKey":"18:55","charType":"word"},{"line":7,"position":6,"textIndopak":"اِذۡ","textUthmani":"إِذْ","verseKey":"18:55","charType":"word"},{"line":7,"position":7,"textIndopak":"جَآءَهُمُ","textUthmani":"جَآءَهُمُ","verseKey":"18:55","charType":"word"},{"line":7,"position":8,"textIndopak":"الۡهُدٰى","textUthmani":"ٱلْهُدَىٰ","verseKey":"18:55","charType":"word"},{"line":7,"position":9,"textIndopak":"وَيَسۡتَغۡفِرُوۡا","textUthmani":"وَيَسْتَغْفِرُوا۟","verseKey":"18:55","charType":"word"}],[{"line":8,"position":10,"textIndopak":"رَبَّهُمۡ","textUthmani":"رَبَّهُمْ","verseKey":"18:55","charType":"word"},{"line":8,"position":11,"textIndopak":"اِلَّاۤ","textUthmani":"إِلَّآ","verseKey":"18:55","charType":"word"},{"line":8,"position":12,"textIndopak":"اَنۡ","textUthmani":"أَن","verseKey":"18:55","charType":"word"},{"line":8,"position":13,"textIndopak":"تَاۡتِيَهُمۡ","textUthmani":"تَأْتِيَهُمْ","verseKey":"18:55","charType":"word"},{"line":8,"position":14,"textIndopak":"سُنَّةُ","textUthmani":"سُنَّةُ","verseKey":"18:55","charType":"word"},{"line":8,"position":15,"textIndopak":"الۡاَوَّلِيۡنَ","textUthmani":"ٱلْأَوَّلِينَ","verseKey":"18:55","charType":"word"},{"line":8,"position":16,"textIndopak":"اَوۡ","textUthmani":"أَوْ","verseKey":"18:55","charType":"word"},{"line":8,"position":17,"textIndopak":"يَاۡتِيَهُمُ","textUthmani":"يَأْتِيَهُمُ","verseKey":"18:55","charType":"word"},{"line":8,"position":18,"textIndopak":"الۡعَذَابُ","textUthmani":"ٱلْعَذَابُ","verseKey":"18:55","charType":"word"},{"line":8,"position":19,"textIndopak":"قُبُلًا‏","textUthmani":"قُبُلًۭا","verseKey":"18:55","charType":"word"},{"line":8,"position":20,"textIndopak":"٥٥","textUthmani":"٥٥","verseKey":"18:55","charType":"end"}],[{"line":9,"position":1,"textIndopak":"وَمَا","textUthmani":"وَمَا","verseKey":"18:56","charType":"word"},{"line":9,"position":2,"textIndopak":"نُرۡسِلُ","textUthmani":"نُرْسِلُ","verseKey":"18:56","charType":"word"},{"line":9,"position":3,"textIndopak":"الۡمُرۡسَلِيۡنَ","textUthmani":"ٱلْمُرْسَلِينَ","verseKey":"18:56","charType":"word"},{"line":9,"position":4,"textIndopak":"اِلَّا","textUthmani":"إِلَّا","verseKey":"18:56","charType":"word"},{"line":9,"position":5,"textIndopak":"مُبَشِّرِيۡنَ","textUthmani":"مُبَشِّرِينَ","verseKey":"18:56","charType":"word"},{"line":9,"position":6,"textIndopak":"وَمُنۡذِرِيۡنَ​ ۚ","textUthmani":"وَمُنذِرِينَ ۚ","verseKey":"18:56","charType":"word"},{"line":9,"position":7,"textIndopak":"وَيُجَادِلُ","textUthmani":"وَيُجَـٰدِلُ","verseKey":"18:56","charType":"word"},{"line":9,"position":8,"textIndopak":"الَّذِيۡنَ","textUthmani":"ٱلَّذِينَ","verseKey":"18:56","charType":"word"}],[{"line":10,"position":9,"textIndopak":"كَفَرُوۡا","textUthmani":"كَفَرُوا۟","verseKey":"18:56","charType":"word"},{"line":10,"position":10,"textIndopak":"بِالۡبَاطِلِ","textUthmani":"بِٱلْبَـٰطِلِ","verseKey":"18:56","charType":"word"},{"line":10,"position":11,"textIndopak":"لِـيُدۡحِضُوۡا","textUthmani":"لِيُدْحِضُوا۟","verseKey":"18:56","charType":"word"},{"line":10,"position":12,"textIndopak":"بِهِ","textUthmani":"بِهِ","verseKey":"18:56","charType":"word"},{"line":10,"position":13,"textIndopak":"الۡحَـقَّ​","textUthmani":"ٱلْحَقَّ ۖ","verseKey":"18:56","charType":"word"},{"line":10,"position":14,"textIndopak":"وَاتَّخَذُوۡۤا","textUthmani":"وَٱتَّخَذُوٓا۟","verseKey":"18:56","charType":"word"},{"line":10,"position":15,"textIndopak":"اٰيٰتِىۡ","textUthmani":"ءَايَـٰتِى","verseKey":"18:56","charType":"word"},{"line":10,"position":16,"textIndopak":"وَمَاۤ","textUthmani":"وَمَآ","verseKey":"18:56","charType":"word"},{"line":10,"position":17,"textIndopak":"اُنۡذِرُوۡا","textUthmani":"أُنذِرُوا۟","verseKey":"18:56","charType":"word"}],[{"line":11,"position":18,"textIndopak":"هُزُوًا‏","textUthmani":"هُزُوًۭا","verseKey":"18:56","charType":"word"},{"line":11,"position":19,"textIndopak":"٥٦","textUthmani":"٥٦","verseKey":"18:56","charType":"end"},{"line":11,"position":1,"textIndopak":"وَمَنۡ","textUthmani":"وَمَنْ","verseKey":"18:57","charType":"word"},{"line":11,"position":2,"textIndopak":"اَظۡلَمُ","textUthmani":"أَظْلَمُ","verseKey":"18:57","charType":"word"},{"line":11,"position":3,"textIndopak":"مِمَّنۡ","textUthmani":"مِمَّن","verseKey":"18:57","charType":"word"},{"line":11,"position":4,"textIndopak":"ذُكِّرَ","textUthmani":"ذُكِّرَ","verseKey":"18:57","charType":"word"},{"line":11,"position":5,"textIndopak":"بِاٰيٰتِ","textUthmani":"بِـَٔايَـٰتِ","verseKey":"18:57","charType":"word"},{"line":11,"position":6,"textIndopak":"رَبِّهٖ","textUthmani":"رَبِّهِۦ","verseKey":"18:57","charType":"word"},{"line":11,"position":7,"textIndopak":"فَاَعۡرَضَ","textUthmani":"فَأَعْرَضَ","verseKey":"18:57","charType":"word"},{"line":11,"position":8,"textIndopak":"عَنۡهَا","textUthmani":"عَنْهَا","verseKey":"18:57","charType":"word"},{"line":11,"position":9,"textIndopak":"وَنَسِىَ","textUthmani":"وَنَسِىَ","verseKey":"18:57","charType":"word"}],[{"line":12,"position":10,"textIndopak":"مَا","textUthmani":"مَا","verseKey":"18:57","charType":"word"},{"line":12,"position":11,"textIndopak":"قَدَّمَتۡ","textUthmani":"قَدَّمَتْ","verseKey":"18:57","charType":"word"},{"line":12,"position":12,"textIndopak":"يَدٰهُ​ ؕ","textUthmani":"يَدَاهُ ۚ","verseKey":"18:57","charType":"word"},{"line":12,"position":13,"textIndopak":"اِنَّا","textUthmani":"إِنَّا","verseKey":"18:57","charType":"word"},{"line":12,"position":14,"textIndopak":"جَعَلۡنَا","textUthmani":"جَعَلْنَا","verseKey":"18:57","charType":"word"},{"line":12,"position":15,"textIndopak":"عَلٰى","textUthmani":"عَلَىٰ","verseKey":"18:57","charType":"word"},{"line":12,"position":16,"textIndopak":"قُلُوۡبِهِمۡ","textUthmani":"قُلُوبِهِمْ","verseKey":"18:57","charType":"word"},{"line":12,"position":17,"textIndopak":"اَكِنَّةً","textUthmani":"أَكِنَّةً","verseKey":"18:57","charType":"word"},{"line":12,"position":18,"textIndopak":"اَنۡ","textUthmani":"أَن","verseKey":"18:57","charType":"word"},{"line":12,"position":19,"textIndopak":"يَّفۡقَهُوۡهُ","textUthmani":"يَفْقَهُوهُ","verseKey":"18:57","charType":"word"},{"line":12,"position":20,"textIndopak":"وَفِىۡۤ","textUthmani":"وَفِىٓ","verseKey":"18:57","charType":"word"}],[{"line":13,"position":21,"textIndopak":"اٰذَانِهِمۡ","textUthmani":"ءَاذَانِهِمْ","verseKey":"18:57","charType":"word"},{"line":13,"position":22,"textIndopak":"وَقۡرًا​ ؕ","textUthmani":"وَقْرًۭا ۖ","verseKey":"18:57","charType":"word"},{"line":13,"position":23,"textIndopak":"وَاِنۡ","textUthmani":"وَإِن","verseKey":"18:57","charType":"word"},{"line":13,"position":24,"textIndopak":"تَدۡعُهُمۡ","textUthmani":"تَدْعُهُمْ","verseKey":"18:57","charType":"word"},{"line":13,"position":25,"textIndopak":"اِلَى","textUthmani":"إِلَى","verseKey":"18:57","charType":"word"},{"line":13,"position":26,"textIndopak":"الۡهُدٰى","textUthmani":"ٱلْهُدَىٰ","verseKey":"18:57","charType":"word"},{"line":13,"position":27,"textIndopak":"فَلَنۡ","textUthmani":"فَلَن","verseKey":"18:57","charType":"word"},{"line":13,"position":28,"textIndopak":"يَّهۡتَدُوۡۤا","textUthmani":"يَهْتَدُوٓا۟","verseKey":"18:57","charType":"word"},{"line":13,"position":29,"textIndopak":"اِذًا","textUthmani":"إِذًا","verseKey":"18:57","charType":"word"},{"line":13,"position":30,"textIndopak":"اَبَدًا‏","textUthmani":"أَبَدًۭا","verseKey":"18:57","charType":"word"},{"line":13,"position":31,"textIndopak":"٥٧","textUthmani":"٥٧","verseKey":"18:57","charType":"end"}],[{"line":14,"position":1,"textIndopak":"وَرَبُّكَ","textUthmani":"وَرَبُّكَ","verseKey":"18:58","charType":"word"},{"line":14,"position":2,"textIndopak":"الۡغَفُوۡرُ","textUthmani":"ٱلْغَفُورُ","verseKey":"18:58","charType":"word"},{"line":14,"position":3,"textIndopak":"ذُوۡ","textUthmani":"ذُو","verseKey":"18:58","charType":"word"},{"line":14,"position":4,"textIndopak":"الرَّحۡمَةِ​ ؕ","textUthmani":"ٱلرَّحْمَةِ ۖ","verseKey":"18:58","charType":"word"},{"line":14,"position":5,"textIndopak":"لَوۡ","textUthmani":"لَوْ","verseKey":"18:58","charType":"word"},{"line":14,"position":6,"textIndopak":"يُؤَاخِذُهُمۡ","textUthmani":"يُؤَاخِذُهُم","verseKey":"18:58","charType":"word"},{"line":14,"position":7,"textIndopak":"بِمَا","textUthmani":"بِمَا","verseKey":"18:58","charType":"word"},{"line":14,"position":8,"textIndopak":"كَسَبُوۡا","textUthmani":"كَسَبُوا۟","verseKey":"18:58","charType":"word"},{"line":14,"position":9,"textIndopak":"لَعَجَّلَ","textUthmani":"لَعَجَّلَ","verseKey":"18:58","charType":"word"},{"line":14,"position":10,"textIndopak":"لَهُمُ","textUthmani":"لَهُمُ","verseKey":"18:58","charType":"word"}],[{"line":15,"position":1,"textIndopak":"وَاِذۡ","textUthmani":"وَإِذْ","verseKey":"18:50","charType":"word"},{"line":15,"position":2,"textIndopak":"قُلۡنَا","textUthmani":"قُلْنَا","verseKey":"18:50","charType":"word"},{"line":15,"position":3,"textIndopak":"لِلۡمَلٰۤٮِٕكَةِ","textUthmani":"لِلْمَلَـٰٓئِكَةِ","verseKey":"18:50","charType":"word"},{"line":15,"position":4,"textIndopak":"اسۡجُدُوۡا","textUthmani":"ٱسْجُدُوا۟","verseKey":"18:50","charType":"word"},{"line":15,"position":5,"textIndopak":"لِاٰدَمَ","textUthmani":"لِـَٔادَمَ","verseKey":"18:50","charType":"word"},{"line":15,"position":6,"textIndopak":"فَسَجَدُوۡۤا","textUthmani":"فَسَجَدُوٓا۟","verseKey":"18:50","charType":"word"},{"line":15,"position":7,"textIndopak":"اِلَّاۤ","textUthmani":"إِلَّآ","verseKey":"18:50","charType":"word"},{"line":15,"position":8,"textIndopak":"اِبۡلِيۡسَؕ","textUthmani":"إِبْلِيسَ","verseKey":"18:50","charType":"word"},{"line":15,"position":11,"textIndopak":"الۡعَذَابَ​ ؕ","textUthmani":"ٱلْعَذَابَ ۚ","verseKey":"18:58","charType":"word"},{"line":15,"position":12,"textIndopak":"بَلْ","textUthmani":"بَل","verseKey":"18:58","charType":"word"},{"line":15,"position":13,"textIndopak":"لَّهُمۡ","textUthmani":"لَّهُم","verseKey":"18:58","charType":"word"},{"line":15,"position":14,"textIndopak":"مَّوۡعِدٌ","textUthmani":"مَّوْعِدٌۭ","verseKey":"18:58","charType":"word"},{"line":15,"position":15,"textIndopak":"لَّنۡ","textUthmani":"لَّن","verseKey":"18:58","charType":"word"},{"line":15,"position":16,"textIndopak":"يَّجِدُوۡا","textUthmani":"يَجِدُوا۟","verseKey":"18:58","charType":"word"},{"line":15,"position":17,"textIndopak":"مِنۡ","textUthmani":"مِن","verseKey":"18:58","charType":"word"},{"line":15,"position":18,"textIndopak":"دُوۡنِهٖ","textUthmani":"دُونِهِۦ","verseKey":"18:58","charType":"word"},{"line":15,"position":19,"textIndopak":"مَوۡٮِٕلًا‏","textUthmani":"مَوْئِلًۭا","verseKey":"18:58","charType":"word"},{"line":15,"position":20,"textIndopak":"٥٨","textUthmani":"٥٨","verseKey":"18:58","charType":"end"},{"line":15,"position":1,"textIndopak":"وَتِلۡكَ","textUthmani":"وَتِلْكَ","verseKey":"18:59","charType":"word"}],[{"line":16,"position":9,"textIndopak":"كَانَ","textUthmani":"كَانَ","verseKey":"18:50","charType":"word"},{"line":16,"position":10,"textIndopak":"مِنَ","textUthmani":"مِنَ","verseKey":"18:50","charType":"word"},{"line":16,"position":11,"textIndopak":"الۡجِنِّ","textUthmani":"ٱلْجِنِّ","verseKey":"18:50","charType":"word"},{"line":16,"position":12,"textIndopak":"فَفَسَقَ","textUthmani":"فَفَسَقَ","verseKey":"18:50","charType":"word"},{"line":16,"position":13,"textIndopak":"عَنۡ","textUthmani":"عَنْ","verseKey":"18:50","charType":"word"},{"line":16,"position":14,"textIndopak":"اَمۡرِ","textUthmani":"أَمْرِ","verseKey":"18:50","charType":"word"},{"line":16,"position":15,"textIndopak":"رَبِّهٖؕ","textUthmani":"رَبِّهِۦٓ ۗ","verseKey":"18:50","charType":"word"},{"line":16,"position":16,"textIndopak":"اَفَتَـتَّخِذُوۡنَهٗ","textUthmani":"أَفَتَتَّخِذُونَهُۥ","verseKey":"18:50","charType":"word"},{"line":16,"position":17,"textIndopak":"وَذُرِّيَّتَهٗۤ","textUthmani":"وَذُرِّيَّتَهُۥٓ","verseKey":"18:50","charType":"word"},{"line":16,"position":18,"textIndopak":"اَوۡلِيَآءَ","textUthmani":"أَوْلِيَآءَ","verseKey":"18:50","charType":"word"},{"line":16,"position":2,"textIndopak":"الۡقُرٰٓى","textUthmani":"ٱلْقُرَىٰٓ","verseKey":"18:59","charType":"word"},{"line":16,"position":3,"textIndopak":"اَهۡلَكۡنٰهُمۡ","textUthmani":"أَهْلَكْنَـٰهُمْ","verseKey":"18:59","charType":"word"},{"line":16,"position":4,"textIndopak":"لَمَّا","textUthmani":"لَمَّا","verseKey":"18:59","charType":"word"},{"line":16,"position":5,"textIndopak":"ظَلَمُوۡا","textUthmani":"ظَلَمُوا۟","verseKey":"18:59","charType":"word"},{"line":16,"position":6,"textIndopak":"وَجَعَلۡنَا","textUthmani":"وَجَعَلْنَا","verseKey":"18:59","charType":"word"},{"line":16,"position":7,"textIndopak":"لِمَهۡلِكِهِمۡ","textUthmani":"لِمَهْلِكِهِم","verseKey":"18:59","charType":"word"},{"line":16,"position":8,"textIndopak":"مَّوۡعِدًا‏","textUthmani":"مَّوْعِدًۭا","verseKey":"18:59","charType":"word"},{"line":16,"position":9,"textIndopak":"٥٩","textUthmani":"٥٩","verseKey":"18:59","charType":"end"},{"line":16,"position":1,"textIndopak":"وَاِذۡ","textUthmani":"وَإِذْ","verseKey":"18:60","charType":"word"},{"line":16,"position":2,"textIndopak":"قَالَ","textUthmani":"قَالَ","verseKey":"18:60","charType":"word"}]]}